gatpack/__init__.py
gatpack/config.py
gatpack/main.py
gatpack/cli/__init__.py
gatpack/cli/build.py
gatpack/cli/combine.py
gatpack/cli/compose.py
gatpack/cli/error_handling.py
gatpack/cli/examples.py
gatpack/cli/footer.py
gatpack/cli/infer.py
gatpack/cli/init.py
gatpack/cli/interactive.py
gatpack/cli/main.py
gatpack/cli/options.py
gatpack/cli/render.py
gatpack/core/__init__.py
gatpack/core/add_footer_to_pdf.py
gatpack/core/build_pdf_from_latex.py
gatpack/core/combine_pdfs.py
gatpack/core/exceptions.py
gatpack/core/infer_and_run_command.py
gatpack/core/initialize_project.py
gatpack/core/load_compose.py
gatpack/core/render_jinja.py
gatpack/core/run_pipeline.py
gatpack/schema/GatPackCompose.py
gatpack/schema/generate_json_schema.py
gatpack/schema/json/GatPackCompose.schema.json
gatpack-0.1.4.dist-info/METADATA
gatpack-0.1.4.dist-info/WHEEL
gatpack-0.1.4.dist-info/entry_points.txt
gatpack-0.1.4.dist-info/licenses/LICENSE
gatpack-0.1.4.dist-info/RECORD
