Metadata-Version: 2.4
Name: gatpack
Version: 0.1.4
Summary: A PDF and website templating tool
Project-URL: Repository, https://github.com/GatlenCulp/GatPack
Author-email: Gatlen Culp <GatlenCulp@gmail.com>
License: 
License-File: LICENSE
Classifier: License :: OSI Approved :: MIT License
Classifier: Programming Language :: Python :: 3
Requires-Python: >=3.9
Requires-Dist: cookiecutter>=2.6.0
Requires-Dist: jinja2>=3.1.5
Requires-Dist: loguru>=0.7.3
Requires-Dist: orjson>=3.10.15
Requires-Dist: pydantic>=2.10.3
Requires-Dist: pypdf>=5.1.0
Requires-Dist: python-dotenv>=1.0.0
Requires-Dist: reportlab>=4.2.5
Requires-Dist: rich>=13.9.4
Requires-Dist: typer>=0.15.1
